tree_to_table/__init__.py
tree_to_table/mappers/__init__.py
tree_to_table/mappers/base.py
tree_to_table/mappers/mappers.py
tree_to_table/sqlalchemy/__init__.py
tree_to_table/sqlalchemy/column.py
tree_to_table/sqlalchemy/transforms.py
tree_to_table/table/__init__.py
tree_to_table/table/table.py
tree_to_table/test.py
tree_to_table/transforms/__init__.py
tree_to_table/transforms/base.py
tree_to_table/transforms/transforms.py
tree_to_table-0.1.0.dist-info/LICENSE
tree_to_table-0.1.0.dist-info/WHEEL
tree_to_table-0.1.0.dist-info/METADATA
tree_to_table-0.1.0.dist-info/RECORD
